README.md
setup.cfg
setup.py
uk_charts_api/__init__.py
uk_charts_api/db.py
uk_charts_api/deezer.py
uk_charts_api/endpoints.py
uk_charts_api/mb.py
uk_charts_api/official_charts.py
uk_charts_api/spotify.py
uk_charts_api/sql.py
uk_charts_api/tag.py
uk_charts_api/utils.py
uk_charts_api.egg-info/PKG-INFO
uk_charts_api.egg-info/SOURCES.txt
uk_charts_api.egg-info/dependency_links.txt
uk_charts_api.egg-info/requires.txt
uk_charts_api.egg-info/top_level.txt
uk_charts_api/models/__init__.py
uk_charts_api/models/chart.py
uk_charts_api/models/deezer.py
uk_charts_api/models/exception.py