Metadata-Version: 2.1
Name: uk-charts-api
Version: 1.0.5
Summary: Python package to get deezer info for UK Top 40 charts
Home-page: https://github.com/cmclaughlin/UK-Charts-API
Author: Connor McLaughlin
License: UNKNOWN
Platform: UNKNOWN
Classifier: Development Status :: 5 - Production/Stable
Classifier: License :: OSI Approved :: GNU General Public License v3 (GPLv3)
Classifier: Topic :: Multimedia :: Sound/Audio
Requires-Python: >=3.6
